[
    {
        "id": "s00001701",
        "speaker": "system",
        "intent": "教える",
        "slots": {
            "観光地の設備": "障害者",
            "観光地の喫煙可否": "不明"
        }
    },
    {
        "id": "s00000181",
        "speaker": "system",
        "intent": "肯定的な反応を示す",
        "slots": {
            "ユーザの観光の同行者": "一人",
            "ユーザが希望する交通手段": "希望なし"
        }
    },
    {
        "id": "s00001462",
        "speaker": "system",
        "intent": "教える",
        "slots": {
            "観光地での観光の所要時間": "60分以上90分未満",
            "観光地におすすめな時期": "秋"
        }
    },
    {
        "id": "s00001513",
        "speaker": "system",
        "intent": "教える",
        "slots": {
            "観光地におすすめな人": "歴史好き",
            "観光地が雨天でも楽しめるか": "可能"
        }
    },
    {
        "id": "s00001575",
        "speaker": "system",
        "intent": "教える",
        "slots": {
            "観光地の割引": "不明",
            "観光地の手荷物預かりの有無": "なし"
        }
    },
    {
        "id": "s00001928",
        "speaker": "system",
        "intent": "教える",
        "slots": {
            "観光地の飲食物持ち込みの可否": "不明",
            "観光地の撮影可否": "可能"
        }
    },
    {
        "id": "s00001170",
        "speaker": "system",
        "intent": "教える",
        "slots": {
            "観光地の名称": "河口浅間神社",
            "観光地のWi-Fiの有無": "不明"
        }
    },
    {
        "id": "s00001897",
        "speaker": "system",
        "intent": "教える",
        "slots": {
            "観光地の手荷物預かりの有無": "不明",
            "観光地のすいている曜日，時間帯": "不明"
        }
    },
    {
        "id": "s00002023",
        "speaker": "system",
        "intent": "教える",
        "slots": {
            "観光地の撮影可否": "不明",
            "観光地の駐車場の料金": "台原入口24台、黒松入口19台"
        }
    },
    {
        "id": "s00000973",
        "speaker": "system",
        "intent": "質問する",
        "slots": {
            "ユーザが希望する観光所要時間": "?",
            "ユーザがインドア派かアウトドア派か": "?"
        }
    },
    {
        "id": "s00002524",
        "speaker": "system",
        "intent": "観光地をお勧めする",
        "slots": {
            "観光地の駐車場の有無": "あり",
            "観光地におすすめな時期": "夏"
        }
    },
    {
        "id": "s00001639",
        "speaker": "system",
        "intent": "教える",
        "slots": {
            "観光地の設備": "乳幼児",
            "観光地の飲食物持ち込みの可否": "可能"
        }
    },
    {
        "id": "s00002605",
        "speaker": "system",
        "intent": "観光地をお勧めする",
        "slots": {
            "観光地におすすめな人": "家族",
            "観光地が雨天でも楽しめるか": "可能"
        }
    },
    {
        "id": "s00000579",
        "speaker": "system",
        "intent": "肯定的な反応を示す",
        "slots": {
            "ユーザが希望する交通手段": "徒歩",
            "ユーザの希望の観光時間帯": "午後"
        }
    },
    {
        "id": "s00001041",
        "speaker": "system",
        "intent": "教える",
        "slots": {
            "観光地のすいている曜日，時間帯": "平日の午後"
        }
    },
    {
        "id": "s00000789",
        "speaker": "system",
        "intent": "肯定的な反応を示す",
        "slots": {
            "ユーザが希望する観光所要時間": "希望なし",
            "ユーザがインドア派かアウトドア派か": "インドア"
        }
    },
    {
        "id": "s00000641",
        "speaker": "system",
        "intent": "肯定的な反応を示す",
        "slots": {
            "ユーザが希望する観光の季節": "希望なし",
            "ユーザが希望する観光所要時間": "60分以上90分未満"
        }
    },
    {
        "id": "s00000763",
        "speaker": "system",
        "intent": "肯定的な反応を示す",
        "slots": {
            "ユーザが希望する観光所要時間": "30分未満",
            "ユーザの希望の観光時間帯": "朝"
        }
    },
    {
        "id": "s00001076",
        "speaker": "system",
        "intent": "教える",
        "slots": {
            "ユーザの名前（※）": "千葉",
            "観光地におすすめな人": "友達"
        }
    },
    {
        "id": "s00000062",
        "speaker": "system",
        "intent": "肯定的な反応を示す",
        "slots": {
            "ユーザの希望の観光時間帯": "午後"
        }
    }
]