[
    {
        "id": "s00000973",
        "speaker": "system",
        "intent": "情報を教える",
        "slots": {
            "観光地の名称": "富岳風穴",
            "観光地の設備": "乳幼児への対応あり"
        }
    },
    {
        "id": "s00002655",
        "speaker": "system",
        "intent": "観光地の情報を使って客におすすめする",
        "slots": {
            "観光地の名称": "曽爾高原",
            "観光地がインドアかアウトドアか": "インドア",
            "観光地の駐車場の料金": "バス7台"
        }
    },
    {
        "id": "s00001821",
        "speaker": "system",
        "intent": "情報を教える",
        "slots": {
            "観光地の名称": "Wonderful Nature Village",
            "観光地の手荷物預かりの有無": "不明",
            "観光地の飲食物持ち込みの可否": "可能"
        }
    },
    {
        "id": "s00002020",
        "speaker": "system",
        "intent": "情報を教える",
        "slots": {
            "観光地の名称": "新庄東山焼弥瓶窯",
            "観光地のおすすめイベント": "不明",
            "観光地の予約要否": "不可能"
        }
    },
    {
        "id": "s00002113",
        "speaker": "system",
        "intent": "観光地の情報を使って客におすすめする",
        "slots": {
            "客の名前（※）": "村上",
            "観光地の名称": "大山祇神社宝物館"
        }
    },
    {
        "id": "s00001890",
        "speaker": "system",
        "intent": "情報を教える",
        "slots": {
            "観光地の名称": "湖畔りんご園",
            "観光地の飲食物持ち込みの可否": "可能",
            "観光地の撮影可否": "可能"
        }
    },
    {
        "id": "s00002466",
        "speaker": "system",
        "intent": "観光地の情報を使って客におすすめする",
        "slots": {
            "観光地の名称": "出雲大神宮",
            "観光地での観光の所要時間": "30分以上60未満",
            "観光地におすすめな時期": "夏"
        }
    },
    {
        "id": "s00002485",
        "speaker": "system",
        "intent": "観光地の情報を使って客におすすめする",
        "slots": {
            "観光地の名称": "島ノ川渓谷",
            "観光地におすすめな人": "友達",
            "観光地におすすめな時期": "春"
        }
    },
    {
        "id": "s10000040",
        "speaker": "system",
        "intent": "好意的に承知する",
        "slots": {
            "客が観光にかけたい時間": "90分以上"
        }
    },
    {
        "id": "s00001656",
        "speaker": "system",
        "intent": "情報を教える",
        "slots": {
            "観光地の名称": "HYTTER LODGE＆CABINS",
            "観光地の設備": "ペットへの対応あり",
            "観光地の予約要否": "可能"
        }
    },
    {
        "id": "s00002271",
        "speaker": "system",
        "intent": "観光地の情報を使って客におすすめする",
        "slots": {
            "観光地の名称": "あきたブルーベリー農園",
            "観光地のジャンル": "観光牧場・観光農園",
            "観光地の最寄り駅": "相模原"
        }
    },
    {
        "id": "s00001074",
        "speaker": "system",
        "intent": "情報を教える",
        "slots": {
            "客の名前（※）": "坂本",
            "観光地の名称": "建仁寺",
            "観光地の広さ": "不明"
        }
    },
    {
        "id": "s00002390",
        "speaker": "system",
        "intent": "観光地の情報を使って客におすすめする",
        "slots": {
            "観光地の名称": "横浜市歴史博物館",
            "観光地の電話番号": "0897-40-4100",
            "観光地の最寄り駅": "西小倉"
        }
    },
    {
        "id": "s00002636",
        "speaker": "system",
        "intent": "観光地の情報を使って客におすすめする",
        "slots": {
            "観光地の名称": "道の駅 豊根グリーンポート宮嶋",
            "観光地の広さ": "一日あれば十分見て回れるような広さ",
            "観光地の撮影可否": "可能"
        }
    },
    {
        "id": "s00000968",
        "speaker": "system",
        "intent": "情報を教える",
        "slots": {
            "観光地の名称": "道の駅 はなわ",
            "観光地が雨天でも楽しめるか": "可能"
        }
    },
    {
        "id": "s00000950",
        "speaker": "system",
        "intent": "情報を教える",
        "slots": {
            "観光地の名称": "ヒルゼン高原センター ジョイフルパーク",
            "観光地の駐車場の有無": "あり"
        }
    },
    {
        "id": "s00000299",
        "speaker": "system",
        "intent": "好意的に承知する",
        "slots": {
            "客の観光の同行者": "友達",
            "客が観光にかけたい時間": "90分以上"
        }
    },
    {
        "id": "s00002452",
        "speaker": "system",
        "intent": "観光地の情報を使って客におすすめする",
        "slots": {
            "観光地の名称": "猿倉山森林公園",
            "観光地での観光の所要時間": "60分以上90分未満",
            "観光地におすすめな人": "恋人"
        }
    },
    {
        "id": "s00001221",
        "speaker": "system",
        "intent": "情報を教える",
        "slots": {
            "観光地の名称": "花島公園",
            "観光地の駐車場の有無": "あり",
            "観光地の定休日": "遊泳期間7月中旬～8月中旬。"
        }
    },
    {
        "id": "s00001607",
        "speaker": "system",
        "intent": "情報を教える",
        "slots": {
            "観光地の名称": "西郷隆盛像",
            "観光地の手荷物預かりの有無": "なし",
            "観光地の設備": "乳幼児への対応あり"
        }
    }
]