[
    {
        "id": "s00000323",
        "speaker": "system",
        "intent": "好意的に承知する",
        "slots": {
            "客の観光の同行者": "女性",
            "客が観光にかけたい時間": "90分以上"
        }
    },
    {
        "id": "s00001675",
        "speaker": "system",
        "intent": "情報を教える",
        "slots": {
            "観光地の名称": "道の駅「阿久根」",
            "観光地のすいている曜日，時間帯": "不明",
            "観光地の設備": "ペットへの対応なし"
        }
    },
    {
        "id": "s00000117",
        "speaker": "system",
        "intent": "好意的に承知する",
        "slots": {
            "客の名前（※）": "大野",
            "客がインドア派かアウトドア派か": "特になし"
        }
    },
    {
        "id": "s00001122",
        "speaker": "system",
        "intent": "情報を教える",
        "slots": {
            "観光地の名称": "海上自衛隊佐世保史料館",
            "観光地の撮影可否": "可能"
        }
    },
    {
        "id": "s00000263",
        "speaker": "system",
        "intent": "好意的に承知する",
        "slots": {
            "客が希望する観光ジャンル": "遺跡・史跡・城址",
            "客の観光の同行者": "子供"
        }
    },
    {
        "id": "s00001968",
        "speaker": "system",
        "intent": "情報を教える",
        "slots": {
            "観光地の名称": "マキノ高原",
            "観光地がインドアかアウトドアか": "アウトドア",
            "観光地の撮影可否": "可能"
        }
    },
    {
        "id": "s00001670",
        "speaker": "system",
        "intent": "情報を教える",
        "slots": {
            "観光地の名称": "飛騨の里",
            "観光地のすいている曜日，時間帯": "不明",
            "観光地の設備": "乳幼児への対応あり"
        }
    },
    {
        "id": "s00002291",
        "speaker": "system",
        "intent": "観光地の情報を使って客におすすめする",
        "slots": {
            "観光地の名称": "江差追分会館・江差山車会館",
            "観光地の料金": "大人400円、小人200円",
            "観光地での観光の所要時間": "30分未満"
        }
    },
    {
        "id": "s00001821",
        "speaker": "system",
        "intent": "情報を教える",
        "slots": {
            "観光地の名称": "絵島",
            "観光地の手荷物預かりの有無": "あり",
            "観光地の予約要否": "可能"
        }
    },
    {
        "id": "s00000259",
        "speaker": "system",
        "intent": "好意的に承知する",
        "slots": {
            "客の観光の同行者": "歴史好き",
            "客が希望する観光の季節": "冬"
        }
    },
    {
        "id": "s00001678",
        "speaker": "system",
        "intent": "情報を教える",
        "slots": {
            "観光地の名称": "立岩・後ケ浜海水浴場",
            "観光地の設備": "ペットへの対応あり",
            "観光地の利用可能なキャッシュレス決済": "不明"
        }
    },
    {
        "id": "s00001403",
        "speaker": "system",
        "intent": "情報を教える",
        "slots": {
            "観光地の名称": "アクアパレットまつやま",
            "観光地での観光の所要時間": "90分以上",
            "観光地におすすめな人": "家族"
        }
    },
    {
        "id": "s00002264",
        "speaker": "system",
        "intent": "観光地の情報を使って客におすすめする",
        "slots": {
            "観光地の名称": "舞洲陶芸館",
            "観光地の営業時間": "9～20時",
            "観光地が雨天でも楽しめるか": "可能"
        }
    },
    {
        "id": "s00000097",
        "speaker": "system",
        "intent": "好意的に承知する",
        "slots": {
            "客の名前（※）": "小島",
            "客の本日の同行者": "乳幼児"
        }
    },
    {
        "id": "s00002067",
        "speaker": "system",
        "intent": "情報を教える",
        "slots": {
            "観光地の名称": "円正寺のシダレザクラ",
            "観光地がインドアかアウトドアか": "インドア",
            "観光地の広さ": "一日あれば十分見て回れるような広さ"
        }
    },
    {
        "id": "s00000174",
        "speaker": "system",
        "intent": "好意的に承知する",
        "slots": {
            "客の観光の同行者": "ペット",
            "客が希望する交通手段": "公共交通機関"
        }
    },
    {
        "id": "s00000612",
        "speaker": "system",
        "intent": "好意的に承知する",
        "slots": {
            "客の希望の観光時間帯": "未定",
            "客が希望する食べ物": "冷麺"
        }
    },
    {
        "id": "s00000193",
        "speaker": "system",
        "intent": "好意的に承知する",
        "slots": {
            "客の観光の同行者": "子供",
            "客が希望する食べ物": "ラーメン"
        }
    },
    {
        "id": "s00001920",
        "speaker": "system",
        "intent": "情報を教える",
        "slots": {
            "観光地の名称": "千秋公園",
            "観光地の飲食物持ち込みの可否": "不可能",
            "観光地がインドアかアウトドアか": "インドア"
        }
    },
    {
        "id": "s00000257",
        "speaker": "system",
        "intent": "好意的に承知する",
        "slots": {
            "客の観光の同行者": "歴史好き",
            "客が希望する観光の季節": "夏"
        }
    }
]