[
    {
        "id": "s00002523",
        "speaker": "system",
        "intent": "観光地の情報を使って客におすすめする",
        "slots": {
            "観光地におすすめな人": "女性",
            "観光地の名称": "松倉城跡",
            "観光地におすすめな時期": "夏"
        }
    },
    {
        "id": "s00001904",
        "speaker": "system",
        "intent": "情報を教える",
        "slots": {
            "観光地の名称": "絵島",
            "観光地の釣りの可否": "不可能",
            "観光地の飲食物持ち込みの可否": "不明"
        }
    },
    {
        "id": "s00002530",
        "speaker": "system",
        "intent": "観光地の情報を使って客におすすめする",
        "slots": {
            "観光地におすすめな人": "家族",
            "観光地の名称": "春花園BONSAI美術館",
            "観光地におすすめな時期": "春"
        }
    },
    {
        "id": "s00000240",
        "speaker": "system",
        "intent": "肯定的な反応を示す",
        "slots": {
            "客が希望する観光の季節": "秋",
            "客の観光の同行者": "未定"
        }
    },
    {
        "id": "s00000389",
        "speaker": "system",
        "intent": "肯定的な反応を示す",
        "slots": {
            "客の希望の観光時間帯": "午後",
            "客の観光の同行者": "歴史好き"
        }
    },
    {
        "id": "s00000578",
        "speaker": "system",
        "intent": "肯定的な反応を示す",
        "slots": {
            "客が希望する交通手段": "未定",
            "客がインドア派かアウトドア派か": "インドア"
        }
    },
    {
        "id": "s00002419",
        "speaker": "system",
        "intent": "観光地の情報を使って客におすすめする",
        "slots": {
            "観光地の車でのアクセス": "圏央道市原鶴舞ICから国道297号経由33km45分",
            "観光地の名称": "吉田海岸",
            "観光地におすすめな時期": "秋"
        }
    },
    {
        "id": "s00001375",
        "speaker": "system",
        "intent": "情報を教える",
        "slots": {
            "観光地におすすめな人": "友達",
            "観光地の名称": "ネスタ リゾート 神戸",
            "観光地の電話番号": "0893-24-2664"
        }
    },
    {
        "id": "s00001164",
        "speaker": "system",
        "intent": "情報を教える",
        "slots": {
            "観光地におすすめな人": "恋人",
            "観光地の名称": "竹生島",
            "観光地のジャンル": "食料品・地酒"
        }
    },
    {
        "id": "s00000759",
        "speaker": "system",
        "intent": "肯定的な反応を示す",
        "slots": {
            "客の希望の観光時間帯": "朝",
            "客が希望する観光所要時間": "30分未満"
        }
    },
    {
        "id": "s00002506",
        "speaker": "system",
        "intent": "観光地の情報を使って客におすすめする",
        "slots": {
            "観光地の名称": "チロリン村キャンプグランド",
            "観光地での観光の所要時間": "90分以上",
            "観光地におすすめな時期": "春"
        }
    },
    {
        "id": "s00001520",
        "speaker": "system",
        "intent": "情報を教える",
        "slots": {
            "観光地の名称": "津鼻崎公園",
            "観光地の駐車場の料金": "1日普通車1000円、大型車3000円、中型車2000円、二輪車300円",
            "観光地のお土産": "伝統工芸品"
        }
    },
    {
        "id": "s00002520",
        "speaker": "system",
        "intent": "観光地の情報を使って客におすすめする",
        "slots": {
            "観光地におすすめな人": "友達",
            "観光地の名称": "十和田神社",
            "観光地におすすめな時期": "秋"
        }
    },
    {
        "id": "s00002098",
        "speaker": "system",
        "intent": "情報を教える",
        "slots": {
            "観光地の喫煙可否": "不可能",
            "観光地の名称": "御座白浜観光農園きゃんぷ村",
            "観光地の利用可能なキャッシュレス決済": "クレジットカード"
        }
    },
    {
        "id": "s00002592",
        "speaker": "system",
        "intent": "観光地の情報を使って客におすすめする",
        "slots": {
            "観光地の設備": "ペットへの対応あり",
            "観光地の名称": "南禅寺天授庵",
            "観光地の利用可能なキャッシュレス決済": "クレジットカード"
        }
    },
    {
        "id": "s00000700",
        "speaker": "system",
        "intent": "肯定的な反応を示す",
        "slots": {
            "客の希望の観光時間帯": "夜",
            "客が希望する観光の季節": "希望なし"
        }
    },
    {
        "id": "s00002632",
        "speaker": "system",
        "intent": "観光地の情報を使って客におすすめする",
        "slots": {
            "観光地のすいている曜日，時間帯": "平日の午後",
            "観光地の名称": "マリンパーク海水浴場",
            "観光地の撮影可否": "可能"
        }
    },
    {
        "id": "s00002267",
        "speaker": "system",
        "intent": "観光地の情報を使って客におすすめする",
        "slots": {
            "観光地におすすめな人": "子供",
            "観光地の名称": "鮎正宗酒造"
        }
    },
    {
        "id": "s00001294",
        "speaker": "system",
        "intent": "情報を教える",
        "slots": {
            "観光地の車でのアクセス": "東北道鹿沼ICからさつきロード経由7km15分",
            "観光地が雨天でも楽しめるか": "不可能",
            "観光地の名称": "日光東照宮 神厩舎"
        }
    },
    {
        "id": "s00000262",
        "speaker": "system",
        "intent": "肯定的な反応を示す",
        "slots": {
            "客が希望する観光ジャンル": "観光道路",
            "客の観光の同行者": "子供"
        }
    }
]