[
    {
        "id": "s00002529",
        "speaker": "system",
        "intent": "観光地の情報を使って客におすすめする",
        "slots": {
            "観光地におすすめな人": "恋人",
            "観光地の名称": "守谷海水浴場",
            "観光地におすすめな時期": "冬"
        }
    },
    {
        "id": "s00000103",
        "speaker": "system",
        "intent": "肯定的な反応を示す",
        "slots": {
            "客の本日の同行者": "女性",
            "客の名前（※）": "佐野"
        }
    },
    {
        "id": "s00000146",
        "speaker": "system",
        "intent": "肯定的な反応を示す",
        "slots": {
            "客が希望する交通手段": "車",
            "客の観光の同行者": "ペット"
        }
    },
    {
        "id": "s00000318",
        "speaker": "system",
        "intent": "肯定的な反応を示す",
        "slots": {
            "客が希望する観光所要時間": "60分以上90分未満",
            "客の観光の同行者": "一人"
        }
    },
    {
        "id": "s00000455",
        "speaker": "system",
        "intent": "肯定的な反応を示す",
        "slots": {
            "客が希望する交通手段": "バス",
            "客が希望する観光の季節": "未定"
        }
    },
    {
        "id": "s00001161",
        "speaker": "system",
        "intent": "情報を教える",
        "slots": {
            "観光地におすすめな人": "子供",
            "観光地の名称": "天王寺動物園",
            "観光地のジャンル": "歴史的建造物"
        }
    },
    {
        "id": "s00000164",
        "speaker": "system",
        "intent": "肯定的な反応を示す",
        "slots": {
            "客が希望する交通手段": "電車",
            "客の観光の同行者": "恋人"
        }
    },
    {
        "id": "s00000375",
        "speaker": "system",
        "intent": "肯定的な反応を示す",
        "slots": {
            "客の希望の観光時間帯": "日中",
            "客の観光の同行者": "家族"
        }
    },
    {
        "id": "s00002162",
        "speaker": "system",
        "intent": "観光地の情報を使って客におすすめする",
        "slots": {
            "観光地の名称": "アンティーク資料館",
            "客の名前（※）": "原"
        }
    },
    {
        "id": "s00002290",
        "speaker": "system",
        "intent": "観光地の情報を使って客におすすめする",
        "slots": {
            "観光地の喫煙可否": "可能",
            "観光地の名称": "HYTTER LODGE＆CABINS"
        }
    },
    {
        "id": "s00002405",
        "speaker": "system",
        "intent": "観光地の情報を使って客におすすめする",
        "slots": {
            "観光地の車でのアクセス": "名神高速京都東ICから県道143号経由8.",
            "観光地の名称": "八女市上陽地区一円のほたる",
            "観光地の駐車場の有無": "あり"
        }
    },
    {
        "id": "s00002597",
        "speaker": "system",
        "intent": "観光地の情報を使って客におすすめする",
        "slots": {
            "観光地の設備": "障害者への対応あり",
            "観光地の名称": "フォレストアドベンチャー・おおひら",
            "観光地がインドアかアウトドアか": "インドア"
        }
    },
    {
        "id": "s00000347",
        "speaker": "system",
        "intent": "肯定的な反応を示す",
        "slots": {
            "客の希望の観光時間帯": "未定",
            "客の観光の同行者": "女性"
        }
    },
    {
        "id": "s00002574",
        "speaker": "system",
        "intent": "観光地の情報を使って客におすすめする",
        "slots": {
            "観光地の設備": "ペットへの対応あり",
            "観光地の名称": "松倉城跡",
            "観光地の飲食物持ち込みの可否": "可能"
        }
    },
    {
        "id": "s00002432",
        "speaker": "system",
        "intent": "観光地の情報を使って客におすすめする",
        "slots": {
            "観光地におすすめな人": "家族",
            "観光地の名称": "ふるやファーム",
            "観光地の最寄り駅": "長浜"
        }
    },
    {
        "id": "s00001243",
        "speaker": "system",
        "intent": "情報を教える",
        "slots": {
            "観光地の名称": "国営武蔵丘陵森林公園",
            "観光地の料金": "ロープウェイ往復大人3200円、冬期は2200円",
            "観光地におすすめな時期": "春"
        }
    },
    {
        "id": "s00001547",
        "speaker": "system",
        "intent": "情報を教える",
        "slots": {
            "観光地の名称": "旧伴家住宅",
            "観光地の予約要否": "不明",
            "観光地の割引": "子供とお年寄り、障害を持つ方に対して割引がある"
        }
    },
    {
        "id": "s00000734",
        "speaker": "system",
        "intent": "肯定的な反応を示す",
        "slots": {
            "客が希望する観光ジャンル": "キャンプ・バーベキュー",
            "客の希望の観光時間帯": "午後"
        }
    },
    {
        "id": "s00001452",
        "speaker": "system",
        "intent": "情報を教える",
        "slots": {
            "観光地におすすめな人": "恋人",
            "観光地の名称": "守谷海水浴場",
            "観光地におすすめな時期": "夏"
        }
    },
    {
        "id": "s00000212",
        "speaker": "system",
        "intent": "肯定的な反応を示す",
        "slots": {
            "客が希望する観光の季節": "希望なし",
            "客の観光の同行者": "子供"
        }
    }
]