[
    {
        "id": "s00002376",
        "speaker": "system",
        "intent": "観光地の情報を使って客におすすめする",
        "slots": {
            "観光地の名称": "石地海水浴場",
            "観光地での観光の所要時間": "30分未満",
            "観光地の電話番号": "0274-22-0977"
        }
    },
    {
        "id": "s00001015",
        "speaker": "system",
        "intent": "情報を教える",
        "slots": {
            "客の名前（※）": "内田",
            "観光地の名称": "剣ケ池",
            "観光地の最寄り駅": "愛・地球博記念公園"
        }
    },
    {
        "id": "s00001197",
        "speaker": "system",
        "intent": "情報を教える",
        "slots": {
            "観光地の名称": "箱根強羅公園 箱根クラフトハウス",
            "観光地の定休日": "月曜、祝日の翌日、6月上旬に4日間程度の休館あり",
            "観光地の車でのアクセス": "第三京浜道路港北ICから2km4分。"
        }
    },
    {
        "id": "s00000340",
        "speaker": "system",
        "intent": "好意的に承知する",
        "slots": {
            "客の希望の観光時間帯": "未定",
            "客の観光の同行者": "未定"
        }
    },
    {
        "id": "s00002136",
        "speaker": "system",
        "intent": "観光地の情報を使って客におすすめする",
        "slots": {
            "客の名前（※）": "山本",
            "観光地の名称": "サナシオン・スパ",
            "観光地の車でのアクセス": "中央道双葉SAから県道101号経由15km30分。"
        }
    },
    {
        "id": "s00000495",
        "speaker": "system",
        "intent": "好意的に承知する",
        "slots": {
            "客が観光にかけたい時間": "希望なし",
            "客が希望する交通手段": "車"
        }
    },
    {
        "id": "s00000088",
        "speaker": "system",
        "intent": "好意的に承知する",
        "slots": {
            "客の名前（※）": "市川",
            "客が希望する観光の季節": "冬"
        }
    },
    {
        "id": "s00000469",
        "speaker": "system",
        "intent": "好意的に承知する",
        "slots": {
            "客が希望する観光の季節": "秋",
            "客が希望する交通手段": "電車"
        }
    },
    {
        "id": "s00001270",
        "speaker": "system",
        "intent": "情報を教える",
        "slots": {
            "観光地の名称": "日光東照宮 陽明門",
            "観光地の車でのアクセス": "鳥取道河原ICから県道324号経由15分",
            "観光地の駐車場の有無": "なし"
        }
    },
    {
        "id": "s00001743",
        "speaker": "system",
        "intent": "情報を教える",
        "slots": {
            "観光地の名称": "二荒山神社 化燈籠",
            "観光地のWi-Fiの有無": "不明",
            "観光地の撮影可否": "可能"
        }
    },
    {
        "id": "s00001846",
        "speaker": "system",
        "intent": "情報を教える",
        "slots": {
            "観光地の名称": "飛騨高山宮川朝市",
            "観光地の広さ": "一日あれば十分見て回れるような広さ",
            "観光地の手荷物預かりの有無": "なし"
        }
    },
    {
        "id": "s00000156",
        "speaker": "system",
        "intent": "好意的に承知する",
        "slots": {
            "客の観光の同行者": "恋人",
            "客が希望する交通手段": "希望なし"
        }
    },
    {
        "id": "s00001685",
        "speaker": "system",
        "intent": "情報を教える",
        "slots": {
            "観光地の名称": "淡路市立陶芸館",
            "観光地の広さ": "不明",
            "観光地の設備": "乳幼児への対応なし"
        }
    },
    {
        "id": "s00000205",
        "speaker": "system",
        "intent": "好意的に承知する",
        "slots": {
            "客の観光の同行者": "未定",
            "客が希望する観光の季節": "冬"
        }
    },
    {
        "id": "s00000458",
        "speaker": "system",
        "intent": "好意的に承知する",
        "slots": {
            "客が希望する観光の季節": "夏",
            "客が希望する交通手段": "未定"
        }
    },
    {
        "id": "s00002486",
        "speaker": "system",
        "intent": "観光地の情報を使って客におすすめする",
        "slots": {
            "観光地の名称": "TAC葛岡ウォーターパーク",
            "観光地のWi-Fiの有無": "あり",
            "観光地の設備": "障害者への対応なし"
        }
    },
    {
        "id": "s00002312",
        "speaker": "system",
        "intent": "観光地の情報を使って客におすすめする",
        "slots": {
            "観光地の名称": "多可町余暇村公園",
            "観光地での観光の所要時間": "60分以上90分未満",
            "観光地の公共交通機関でのアクセス": "京都丹後鉄道網野駅→丹後海陸交通バス経ケ岬行きで35分、バス停：竹野下車、徒歩5分"
        }
    },
    {
        "id": "s00002085",
        "speaker": "system",
        "intent": "観光地の情報を使って客におすすめする",
        "slots": {
            "観光地の名称": "江差追分会館・江差山車会館",
            "観光地の営業時間": "有料施設のみ6時30分～21時"
        }
    },
    {
        "id": "s00001077",
        "speaker": "system",
        "intent": "情報を教える",
        "slots": {
            "観光地の名称": "小松市立本陣記念美術館",
            "観光地の定休日": "休園日要問合せ"
        }
    },
    {
        "id": "s00000791",
        "speaker": "system",
        "intent": "好意的に承知する",
        "slots": {
            "客が観光にかけたい時間": "30分以上60未満",
            "客がインドア派かアウトドア派か": "インドア"
        }
    }
]